fibresem/__init__.py
fibresem/__main__.py
fibresem/scripts.py
fibresem/addons/__init__.py
fibresem/addons/renamer.py
fibresem/analysis/__init__.py
fibresem/analysis/analysis_engines.py
fibresem/analysis/fibreanalysis.py
fibresem/analysis/matlabenginehandler.py
fibresem/core/__init__.py
fibresem/core/config.py
fibresem/core/fibresem.py
fibresem/helper/__init__.py
fibresem/helper/clickhelp.py
fibresem/io/__init__.py
fibresem/io/readtif.py
fibresem/io/tifffile/__init__.py
fibresem/io/tifffile/__main__.py
fibresem/io/tifffile/lsm2bin.py
fibresem/io/tifffile/tiffcomment.py
fibresem/io/tifffile/tifffile.py
fibresem/io/tifffile/tifffile_geodb.py
fibresem/matplotlib_scalebar/__init__.py
fibresem/matplotlib_scalebar/_version.py
fibresem/matplotlib_scalebar/dimension.py
fibresem/matplotlib_scalebar/scalebar.py
fibresem/matplotlib_scalebar/test_dimension.py
fibresem/matplotlib_scalebar/test_scalebar.py
fibresem-0.0.4.dist-info/LICENSE
fibresem-0.0.4.dist-info/METADATA
fibresem-0.0.4.dist-info/WHEEL
fibresem-0.0.4.dist-info/top_level.txt
fibresem-0.0.4.dist-info/RECORD
